datacalc/__init__.py
datacalc/bearing.py
algoands-0.1.dist-info/METADATA
algoands-0.1.dist-info/WHEEL
algoands-0.1.dist-info/top_level.txt
algoands-0.1.dist-info/RECORD
